fastapi_responseschema/__init__.py
fastapi_responseschema/_compat.py
fastapi_responseschema/exceptions.py
fastapi_responseschema/helpers.py
fastapi_responseschema/integrations/__init__.py
fastapi_responseschema/integrations/pagination.py
fastapi_responseschema/interfaces.py
fastapi_responseschema/py.typed
fastapi_responseschema/routing.py
fastapi_responseschema-2.1.0.dist-info/LICENSE
fastapi_responseschema-2.1.0.dist-info/METADATA
fastapi_responseschema-2.1.0.dist-info/WHEEL
fastapi_responseschema-2.1.0.dist-info/RECORD
