Metadata-Version: 2.1
Name: fastapi-responseschema
Version: 2.1.0
Summary: Generic and common response schemas for FastAPI
Home-page: https://acwazz.github.io/fastapi-responseschema/
License: MIT
Author: Emanuele Addis
Author-email: ustarjem.acwazz@gmail.com
Requires-Python: >=3.8,<4.0
Classifier: License :: OSI Approved :: MIT License
Classifier: Programming Language :: Python :: 3
Classifier: Programming Language :: Python :: 3.8
Classifier: Programming Language :: Python :: 3.9
Classifier: Programming Language :: Python :: 3.10
Classifier: Programming Language :: Python :: 3.11
Classifier: Programming Language :: Python :: 3.12
Provides-Extra: pagination
Requires-Dist: fastapi (>=0.89.1)
Requires-Dist: fastapi-pagination (>=0,<1) ; extra == "pagination"
Project-URL: Repository, https://github.com/acwazz/fastapi-responseschema
